rats/app/__init__.py
rats/app/_building_di_container.py
rats/app/_building_services.py
rats/app/_dag_di_container.py
rats/app/_io2_di_container.py
rats/app/_io_di_container.py
rats/app/_rats_app.py
rats/app/_rats_app_di_contianer.py
rats/app/_rats_app_plugins.py
rats/app/_rats_app_services.py
rats/app/_session_di_container.py
rats/app/_session_services.py
rats/app/_ux.py
rats/app/py.typed
rats/app_api/__init__.py
rats/app_api/_app.py
rats/app_api/_plugin.py
rats/app_api/_plugin_entry_points.py
rats/app_api/py.typed
rats/examples/__init__.py
rats/examples/io2/__init__.py
rats/examples/io2/__main__.py
rats/examples/io2/_app_plugin.py
rats/examples/io2/_data.py
rats/examples/io2/_di_container.py
rats/examples/io2/_fake_agent.py
rats/examples/io2/_pipeline.py
rats/examples/io2/_user_input.py
rats/examples/py.typed
rats/io/__init__.py
rats/io/_io_data.py
rats/io/_io_defaults.py
rats/io/_io_manager.py
rats/io/_local.py
rats/io/_memory.py
rats/io/_node_output.py
rats/io/_registry_plugins.py
rats/io/_rw_data.py
rats/io/_services.py
rats/io/py.typed
rats/io2/__init__.py
rats/io2/_data.py
rats/io2/_io_plugins.py
rats/io2/_local_json_formattable.py
rats/io2/_local_json_plugin.py
rats/io2/_local_json_writer.py
rats/io2/_local_settings.py
rats/io2/_pipeline_data.py
rats/io2/py.typed
rats/pipelines/__init__.py
rats/pipelines/building/__init__.py
rats/pipelines/building/_builder_client.py
rats/pipelines/building/_node_multiplexing.py
rats/pipelines/building/_node_namespacing.py
rats/pipelines/dag/__init__.py
rats/pipelines/dag/_dag_client.py
rats/pipelines/dag/_structs.py
rats/pipelines/py.typed
rats/pipelines/session/__init__.py
rats/pipelines/session/_contexts.py
rats/pipelines/session/_node_execution.py
rats/pipelines/session/_node_state.py
rats/pipelines/session/_session_client.py
rats/pipelines/session/_session_frame.py
rats/pipelines/session/_session_state.py
rats/services/__init__.py
rats/services/_contexts.py
rats/services/_di_containers.py
rats/services/_executables.py
rats_pipelines-0.1.3.dist-info/METADATA
rats_pipelines-0.1.3.dist-info/WHEEL
rats_pipelines-0.1.3.dist-info/entry_points.txt
rats_pipelines-0.1.3.dist-info/RECORD
