Metadata-Version: 2.1
Name: rats-pipelines
Version: 0.1.3
Summary: Rats Pipelines
Home-page: https://github.com/microsoft/rats/
License: MIT
Keywords: pipelines,machine learning,research
Requires-Python: >=3.10,<4.0
Classifier: License :: OSI Approved :: MIT License
Classifier: Programming Language :: Python :: 3
Classifier: Programming Language :: Python :: 3.10
Classifier: Programming Language :: Python :: 3.11
Classifier: Programming Language :: Python :: 3.12
Requires-Dist: dill
Requires-Dist: furl (>=2.1.3,<3.0.0)
Requires-Dist: kubernetes
Requires-Dist: typing_extensions
Project-URL: Documentation, https://microsoft.github.io/rats/
Project-URL: Repository, https://github.com/microsoft/rats/
